mmkv/__init__.py
mmkv/mmkv.py
sb_tencent_mmkv-0.1.7.dist-info/METADATA
sb_tencent_mmkv-0.1.7.dist-info/WHEEL
sb_tencent_mmkv-0.1.7.dist-info/top_level.txt
sb_tencent_mmkv-0.1.7.dist-info/RECORD
