Metadata-Version: 2.4
Name: sb_tencent_mmkv
Version: 0.1.7
Summary: Tencent MMKV for Python 3.13
Classifier: Programming Language :: Python :: 3.13
Classifier: Operating System :: Microsoft :: Windows
Classifier: Operating System :: POSIX :: Linux
Classifier: Operating System :: MacOS :: MacOS X
Dynamic: classifier
Dynamic: summary
